typeracerbot/__init__.py
typeracerbot/typeracerbot.py
typeracerbot/letters/!.png
"typeracerbot/letters/""."".png"
"typeracerbot/letters/"".png"
"typeracerbot/letters/""A"".png"
"typeracerbot/letters/""B"".png"
"typeracerbot/letters/""C"".png"
"typeracerbot/letters/""D"".png"
"typeracerbot/letters/""E"".png"
"typeracerbot/letters/""F"".png"
"typeracerbot/letters/""G"".png"
"typeracerbot/letters/""H"".png"
"typeracerbot/letters/""I"".png"
"typeracerbot/letters/""J"".png"
"typeracerbot/letters/""K"".png"
"typeracerbot/letters/""L"".png"
"typeracerbot/letters/""M"".png"
"typeracerbot/letters/""N"".png"
"typeracerbot/letters/""O"".png"
"typeracerbot/letters/""P"".png"
"typeracerbot/letters/""Q"".png"
"typeracerbot/letters/""R"".png"
"typeracerbot/letters/""S"".png"
"typeracerbot/letters/""T"".png"
"typeracerbot/letters/""U"".png"
"typeracerbot/letters/""V"".png"
"typeracerbot/letters/""W"".png"
"typeracerbot/letters/""X"".png"
"typeracerbot/letters/""Y"".png"
"typeracerbot/letters/""Z"".png"
typeracerbot/letters/'.png
typeracerbot/letters/(.png
typeracerbot/letters/).png
typeracerbot/letters/*.png
"typeracerbot/letters/,.png"
typeracerbot/letters/-.png
typeracerbot/letters/0.png
typeracerbot/letters/1.png
typeracerbot/letters/2.png
typeracerbot/letters/3.png
typeracerbot/letters/4.png
typeracerbot/letters/5.png
typeracerbot/letters/6.png
typeracerbot/letters/7.png
typeracerbot/letters/8.png
typeracerbot/letters/9.png
typeracerbot/letters/;.png
typeracerbot/letters/?.png
typeracerbot/letters/a.png
typeracerbot/letters/b.png
typeracerbot/letters/c.png
typeracerbot/letters/d.png
typeracerbot/letters/e.png
typeracerbot/letters/f.png
typeracerbot/letters/g.png
typeracerbot/letters/h.png
typeracerbot/letters/i.png
typeracerbot/letters/j.png
typeracerbot/letters/k.png
typeracerbot/letters/l.png
typeracerbot/letters/m.png
typeracerbot/letters/n.png
typeracerbot/letters/o.png
typeracerbot/letters/p.png
typeracerbot/letters/q.png
typeracerbot/letters/r.png
typeracerbot-1.0.1.dist-info/LICENSE
typeracerbot-1.0.1.dist-info/METADATA
typeracerbot-1.0.1.dist-info/WHEEL
typeracerbot-1.0.1.dist-info/top_level.txt
typeracerbot-1.0.1.dist-info/RECORD
